<annotation>
	<folder>image</folder>
	<filename>1751.jpg</filename>
	<path>/home/ostap/Documents/project/ImageWork/Beta1/detectBita/image/1751.jpg</path>
	<source>
		<database>Unknown</database>
	</source>
	<size>
		<width>465</width>
		<height>612</height>
		<depth>3</depth>
	</size>
	<segmented>0</segmented>
	<object>
		<name>bita</name>
		<pose>Unspecified</pose>
		<truncated>0</truncated>
		<difficult>0</difficult>
		<bndbox>
			<xmin>75</xmin>
			<ymin>234</ymin>
			<xmax>352</xmax>
			<ymax>321</ymax>
		</bndbox>
	</object>
</annotation>
