<annotation>
	<folder>image</folder>
	<filename>2000.jpg</filename>
	<path>/home/ostap/Documents/project/ImageWork/Beta1/detectBita/image/2000.jpg</path>
	<source>
		<database>Unknown</database>
	</source>
	<size>
		<width>448</width>
		<height>612</height>
		<depth>3</depth>
	</size>
	<segmented>0</segmented>
	<object>
		<name>bita</name>
		<pose>Unspecified</pose>
		<truncated>0</truncated>
		<difficult>0</difficult>
		<bndbox>
			<xmin>9</xmin>
			<ymin>342</ymin>
			<xmax>166</xmax>
			<ymax>459</ymax>
		</bndbox>
	</object>
</annotation>
